pacote_python_tb/__init__.py
pacote_python_tb/acordes.py
pacote_python_tb/campo_harmonico.py
pacote_python_tb/cli.py
pacote_python_tb/escalas.py
pacote_python_tb-0.1.0.dist-info/LICENSE
pacote_python_tb-0.1.0.dist-info/METADATA
pacote_python_tb-0.1.0.dist-info/WHEEL
pacote_python_tb-0.1.0.dist-info/entry_points.txt
pacote_python_tb-0.1.0.dist-info/RECORD
