Metadata-Version: 2.1
Name: pacote-python-tb
Version: 0.1.0
Summary: Notas musicais é um CLI para ajudar na formação de escalas, acordes e campos harmônicos
License: Beerware
Author: Fernando Pacheco
Author-email: fernandopachecopx@gmail.com
Requires-Python: >=3.12,<4.0
Classifier: Development Status :: 5 - Production/Stable
Classifier: Environment :: Console
Classifier: License :: Other/Proprietary License
Classifier: Natural Language :: Portuguese (Brazilian)
Classifier: Programming Language :: Python :: 3
Classifier: Programming Language :: Python :: 3.12
Classifier: Topic :: Education
Requires-Dist: rich (>=13.9.4,<14.0.0)
Requires-Dist: typer (>=0.13.0,<0.14.0)
Project-URL: Bug Tracker, https://github.com/fernando-pacheco/pacote-python-tb/issues
Project-URL: Códgio, https://github.com/fernando-pacheco/pacote-python-tb
Project-URL: Documentação, https://pacote-python-tb.readthedocs.io/pt/latest/
